{"Scid":1100832,"Name":"Rowan University","Address":"201 Mullica Hill Road","City":"Glassboro","State":"NJ","Zip":"08028","WwwUrl":"https://www.rowan.edu/","Opeid":"00260900","Opeid6":"002609","Iped":"184782","Setting":"Suburban","Location":{"type":"Point","coordinates":[-75.1191177368164,39.7091064453125]},"TestPolicy":{"FirstYearPolicy":"optional","OptionalMessage":"\u003cp\u003ePlease review our \u003ca href=\"https://admissions.rowan.edu/admissions-process/freshman-requirements/standardized-scores.html\" target=\"_blank\" rel=\"noopener noreferrer\"\u003eTest Optional Admissions\u003c/a\u003e website for more information before making your selection.\u003c/p\u003e\n"},"Country":"United States","VerifiedByDataOwner":true,"HasDynamicContent":true,"ScoirApplyEnabled":true,"DisplayAsScoirApply":true,"CoalitionMember":true,"GeneralInfo":{"AdmPhone":"(856) 256-4200","AdmEmail":"admissions@rowan.edu","AdmFax":"856 256-4430","FinPhone":"856 256-4250","FtDegree3":14869,"HasOnCampusHousing":true,"HBCU":false,"HonorsCollege":"","OthRelig":"Not applicable","PublicPrivate":"Public","ResidenceCollege":true,"TotalDegree3":19660,"UnivType":"4 year","SchoolClassifier":"NotClassified"},"FreshEnroll":{"NumApplEnrolled":2555,"NumApplOffered":13948,"NumApplReceived":17923},"TuitionAndExpenses":{"FeesIndistrict":4450,"FeesInstate":4450,"FeesOutstate":4450,"TuitionIndistrict":11250,"TuitionInstate":11250,"TuitionOutstate":21114,"RoomBoard":16553,"BookFees":1665,"StickerInState":33918,"StickerOutState":43782},"AdmissionFreshmen":{"ApplicFeeAmt":65},"Admissions":{"CommonForm":"yes","CoalitionForm":true,"CommonGroup":"yes"},"FinancialAid":{"AverageDebt":21500,"DebtBalanceMedian":35245,"PcFedLoansReceived":49,"PcFinAidReceived":73},"NetPrice":{"NetAverage":22237,"Income1":15180,"Income2":15598,"Income3":19644,"Income4":27596,"Income5":28933},"CalculatedFields":{"AcceptanceRate":77.82179322658037,"SATMin":1100,"SATMax":1310,"SATAvg":1205,"ACTAvg":28,"ACTMin":26,"ACTMax":30},"Sports":{},"Degrees":null,"ApplicationDetails":{"StandardizedTests":{"SATorACT":{"Value":"Optional"},"WithWriting":{"Value":"NotRequired"},"SubjectTests":{"Value":"NotSpecified"}},"SupplementalRequirements":{"EssayOrStatement":{"Value":"Required"},"Resume":{"Value":"NotSpecified"},"Portfolio":{"Value":"Optional"},"Interview":{"Value":"NotSpecified"},"AuditionOrPortfolioReview":{"Value":"NotSpecified"}}},"ApplicationRounds":[{"Name":"Regular Decision","Type":"Regular Decision","DueDate":{"Day":1,"Month":5},"Binding":false}]}