{"Scid":1100640,"Name":"Northwest University","Address":"5520 108th Ave NE","City":"Kirkland","State":"WA","Zip":"98083-0579","WwwUrl":"http://www.northwestu.edu/","Opeid":"00378300","Opeid6":"003783","Iped":"236133","Setting":"Suburban","Location":{"type":"Point","coordinates":[-122.19276428222656,47.65794372558594]},"Country":"United States","VerifiedByDataOwner":true,"ScoirApplyEnabled":false,"DisplayAsScoirApply":false,"CoalitionMember":false,"GeneralInfo":{"AdmPhone":"(425) 889-5231","AdmEmail":"","AdmFax":"425 889-5224","FinPhone":"425 889-5210","FtDegree3":679,"HasOnCampusHousing":true,"HBCU":false,"HonorsCollege":"","OthRelig":"Christian - other","PublicPrivate":"Private - Not For-profit","ResidenceCollege":true,"TotalDegree3":999,"UnivType":"4 year","SchoolClassifier":"NotClassified"},"FreshEnroll":{"NumApplEnrolled":152,"NumApplOffered":516,"NumApplReceived":586},"TuitionAndExpenses":{"FeesIndistrict":500,"FeesInstate":500,"FeesOutstate":500,"TuitionIndistrict":35535,"TuitionInstate":35535,"TuitionOutstate":35535,"RoomBoard":10648,"BookFees":702,"StickerInState":47385,"StickerOutState":47385},"AdmissionFreshmen":{"ApplicFeeAmt":30},"Admissions":{"CommonForm":"yes","CoalitionForm":false,"CommonGroup":"no"},"FinancialAid":{"AverageDebt":23724.5,"DebtBalanceMedian":30946,"PcFedLoansReceived":64,"PcFinAidReceived":92},"NetPrice":{"NetAverage":25917,"Income1":14935,"Income2":15418,"Income3":19757,"Income4":25518,"Income5":31535},"CalculatedFields":{"AcceptanceRate":88.05460750853243,"SATMin":1040,"SATMax":1325,"SATAvg":1182,"ACTAvg":25,"ACTMin":24,"ACTMax":29},"Sports":{},"Degrees":null,"ApplicationDetails":{"StandardizedTests":{"SATorACT":{"Value":"Optional"},"WithWriting":{"Value":"NotSpecified"},"SubjectTests":{"Value":"NotSpecified"}},"SupplementalRequirements":{"EssayOrStatement":{"Value":"Required"},"Resume":{"Value":"NotSpecified"},"Portfolio":{"Value":"NotSpecified"},"Interview":{"Value":"NotSpecified"},"AuditionOrPortfolioReview":{"Value":"NotSpecified"}}},"ApplicationRounds":[{"Name":"Early Action Fall 2026","Type":"Early Action","DueDate":{"Day":15,"Month":11},"Binding":false},{"Name":"Rolling Admission Fall 2026","Type":"Rolling","DueDate":{"Day":24,"Month":7},"Binding":false}]}