{"Scid":1100204,"Name":"Manhattan School of Music","Address":"130 Claremont Avenue","City":"New York","State":"NY","Zip":"10027","WwwUrl":"http://www.msmnyc.edu/","Opeid":"00275900","Opeid6":"002759","Iped":"192712","Setting":"City","Location":{"type":"Point","coordinates":[-73.96133422851562,40.812313079833984]},"Country":"United States","ScoirApplyEnabled":false,"DisplayAsScoirApply":false,"CoalitionMember":false,"GeneralInfo":{"AdmPhone":"(212) 749-2802 ext.4436","AdmEmail":"admissions@msmnyc.edu","AdmFax":"212 749-3025","FinPhone":"212 749-2802, extension 4463","FtDegree3":543,"HasOnCampusHousing":true,"HBCU":false,"HonorsCollege":"","OthRelig":"Not applicable","PublicPrivate":"Private - Not For-profit","ResidenceCollege":true,"TotalDegree3":1097,"UnivType":"4 year","SchoolClassifier":"NotClassified"},"FreshEnroll":{"NumApplEnrolled":142,"NumApplOffered":572,"NumApplReceived":1432},"TuitionAndExpenses":{"FeesIndistrict":1100,"FeesInstate":1100,"FeesOutstate":1100,"TuitionIndistrict":53500,"TuitionInstate":53500,"TuitionOutstate":53500,"RoomBoard":17350,"BookFees":1500,"StickerInState":73450,"StickerOutState":73450},"AdmissionFreshmen":{"ApplicFeeAmt":125},"Admissions":{"CommonForm":"no","CoalitionForm":false,"CommonGroup":"no"},"FinancialAid":{"AverageDebt":23700,"DebtBalanceMedian":23700,"PcFedLoansReceived":32,"PcFinAidReceived":83},"NetPrice":{"NetAverage":51879,"Income1":42437,"Income2":55777,"Income3":57477,"Income4":0,"Income5":59277},"CalculatedFields":{"AcceptanceRate":39.944134078212294,"SATMin":0,"SATMax":0,"SATAvg":0,"ACTAvg":0,"ACTMin":0,"ACTMax":0},"Sports":{},"Degrees":null,"ApplicationDetails":{"StandardizedTests":{"SATorACT":{"Value":"Optional"},"WithWriting":{"Value":"NotRequired"},"SubjectTests":{"Value":"NotSpecified"}},"SupplementalRequirements":{"EssayOrStatement":{"Value":"Required"},"Resume":{"Value":"Required"},"Portfolio":{"Value":"NotSpecified"},"Interview":{"Value":"NotSpecified"},"AuditionOrPortfolioReview":{"Value":"Required"}}},"ApplicationRounds":[{"Name":"Regular Decision","Type":"Regular Decision","DueDate":{"Day":1,"Month":12},"Binding":false}]}