{"Scid":1100622,"Name":"Marshall University","Address":"1 John Marshall Dr","City":"Huntington","State":"WV","Zip":"25755","WwwUrl":"https://www.marshall.edu/","Opeid":"00381500","Opeid6":"003815","Iped":"237525","Setting":"City","Location":{"type":"Point","coordinates":[-82.42896270751953,38.422481536865234]},"Country":"United States","ScoirApplyEnabled":false,"DisplayAsScoirApply":false,"CoalitionMember":false,"GeneralInfo":{"AdmPhone":"(304) 696-3160","AdmEmail":"admissions@marshall.edu","AdmFax":"304 696-3135","FinPhone":"304 696-3162","FtDegree3":8235,"HasOnCampusHousing":true,"HBCU":false,"HonorsCollege":"","OthRelig":"Not applicable","PublicPrivate":"Public","ResidenceCollege":true,"TotalDegree3":11027,"UnivType":"4 year","SchoolClassifier":"NotClassified"},"FreshEnroll":{"NumApplEnrolled":1739,"NumApplOffered":6269,"NumApplReceived":6499},"TuitionAndExpenses":{"FeesIndistrict":1570,"FeesInstate":1570,"FeesOutstate":1570,"TuitionIndistrict":7372,"TuitionInstate":7372,"TuitionOutstate":18724,"RoomBoard":12852,"BookFees":1100,"StickerInState":22894,"StickerOutState":34246},"AdmissionFreshmen":{"ApplicFeeAmt":40},"Admissions":{"CommonForm":"yes","CoalitionForm":false,"CommonGroup":"no"},"FinancialAid":{"AverageDebt":22705,"DebtBalanceMedian":22705,"PcFedLoansReceived":45,"PcFinAidReceived":79},"NetPrice":{"NetAverage":9734,"Income1":4820,"Income2":5572,"Income3":7970,"Income4":12243,"Income5":15496},"CalculatedFields":{"AcceptanceRate":96.46099399907678,"SATMin":890,"SATMax":1130,"SATAvg":1010,"ACTAvg":21,"ACTMin":18,"ACTMax":24},"Sports":{},"Degrees":null,"ApplicationDetails":{"StandardizedTests":{"SATorACT":{"Value":"Optional"},"WithWriting":{"Value":"NotRequired"},"SubjectTests":{"Value":"NotSpecified"}},"SupplementalRequirements":{"EssayOrStatement":{"Value":"NotSpecified"},"Resume":{"Value":"NotSpecified"},"Portfolio":{"Value":"NotSpecified"},"Interview":{"Value":"NotSpecified"},"AuditionOrPortfolioReview":{"Value":"NotSpecified"}}},"ApplicationRounds":[{"Name":"Rolling Admission Spring 2026","Type":"Rolling","DueDate":{"Day":3,"Month":1},"Binding":false},{"Name":"Rolling Admission Summer 2026","Type":"Rolling","DueDate":{"Day":4,"Month":7},"Binding":false},{"Name":"Rolling Admission Fall 2026","Type":"Rolling","DueDate":{"Day":26,"Month":7},"Binding":false}]}