{"Scid":1100980,"Name":"Augsburg University","Address":"2211 Riverside Ave","City":"Minneapolis","State":"MN","Zip":"55454","WwwUrl":"http://www.augsburg.edu/","Opeid":"00233400","Opeid6":"002334","Iped":"173045","Setting":"City","Location":{"type":"Point","coordinates":[-93.24043273925781,44.96630859375]},"Country":"United States","ScoirApplyEnabled":false,"DisplayAsScoirApply":false,"CoalitionMember":false,"GeneralInfo":{"AdmPhone":"(612) 330-1001","AdmEmail":"","AdmFax":"612 330-1590","FinPhone":"612 330-1046","FtDegree3":2445,"HasOnCampusHousing":true,"HBCU":false,"HonorsCollege":"","OthRelig":"Evangelical","PublicPrivate":"Private - Not For-profit","ResidenceCollege":true,"TotalDegree3":3161,"UnivType":"4 year","SchoolClassifier":"NotClassified"},"FreshEnroll":{"NumApplEnrolled":684,"NumApplOffered":3319,"NumApplReceived":4337},"TuitionAndExpenses":{"FeesIndistrict":800,"FeesInstate":800,"FeesOutstate":800,"TuitionIndistrict":43142,"TuitionInstate":43142,"TuitionOutstate":43142,"RoomBoard":16418,"BookFees":1500,"StickerInState":61860,"StickerOutState":61860},"AdmissionFreshmen":{"ApplicFeeAmt":0},"Admissions":{"CommonForm":"yes","CoalitionForm":false,"CommonGroup":"yes"},"FinancialAid":{"AverageDebt":27000,"DebtBalanceMedian":27000,"PcFedLoansReceived":74,"PcFinAidReceived":97},"NetPrice":{"NetAverage":24807,"Income1":21376,"Income2":20901,"Income3":20478,"Income4":24741,"Income5":30427},"CalculatedFields":{"AcceptanceRate":76.52755360848512,"SATMin":0,"SATMax":0,"SATAvg":0,"ACTAvg":0,"ACTMin":0,"ACTMax":0},"Sports":{},"Degrees":null,"ApplicationDetails":{"StandardizedTests":{"SATorACT":{"Value":"Optional"},"WithWriting":{"Value":"Required"},"SubjectTests":{"Value":"NotSpecified"}},"SupplementalRequirements":{"EssayOrStatement":{"Value":"Required"},"Resume":{"Value":"NotSpecified"},"Portfolio":{"Value":"NotSpecified"},"Interview":{"Value":"NotSpecified"},"AuditionOrPortfolioReview":{"Value":"NotSpecified"}}},"ApplicationRounds":[{"Name":"Early Auggie Scholarship - Application Deadline","Type":"Priority","DueDate":{"Day":1,"Month":12},"Binding":false},{"Name":"Rolling","Type":"Rolling","DueDate":{"Day":0,"Month":0},"Binding":false}]}