{"Scid":1100685,"Name":"Illinois Wesleyan University","Address":"1312 N Park St","City":"Bloomington","State":"IL","Zip":"61702-2900","WwwUrl":"http://www.iwu.edu/","Opeid":"00169600","Opeid6":"001696","Iped":"145646","Setting":"City","Location":{"type":"Point","coordinates":[-88.99201202392578,40.48990249633789]},"Country":"United States","ScoirApplyEnabled":false,"DisplayAsScoirApply":false,"CoalitionMember":false,"GeneralInfo":{"AdmPhone":"(309) 556-3031","AdmEmail":"","AdmFax":"309 556-3820","FinPhone":"309 556-3096","FtDegree3":1576,"HasOnCampusHousing":true,"HBCU":false,"HonorsCollege":"","OthRelig":"Not applicable","PublicPrivate":"Private - Not For-profit","ResidenceCollege":true,"TotalDegree3":1576,"UnivType":"4 year","SchoolClassifier":"NotClassified"},"FreshEnroll":{"NumApplEnrolled":441,"NumApplOffered":2768,"NumApplReceived":6128},"TuitionAndExpenses":{"FeesIndistrict":204,"FeesInstate":204,"FeesOutstate":204,"TuitionIndistrict":55500,"TuitionInstate":55500,"TuitionOutstate":55500,"RoomBoard":12930,"BookFees":800,"StickerInState":69434,"StickerOutState":69434},"AdmissionFreshmen":{"ApplicFeeAmt":0},"Admissions":{"CommonForm":"yes","CoalitionForm":false,"CommonGroup":"yes"},"FinancialAid":{"AverageDebt":27000,"DebtBalanceMedian":27000,"PcFedLoansReceived":66,"PcFinAidReceived":99},"NetPrice":{"NetAverage":31310,"Income1":21011,"Income2":24494,"Income3":24284,"Income4":28757,"Income5":35699},"CalculatedFields":{"AcceptanceRate":45.16971279373368,"SATMin":1140,"SATMax":1330,"SATAvg":1235,"ACTAvg":27,"ACTMin":24,"ACTMax":29},"Sports":{},"Degrees":null,"ApplicationDetails":{"StandardizedTests":{"SATorACT":{"Value":"Optional"},"WithWriting":{"Value":"NotSpecified"},"SubjectTests":{"Value":"NotSpecified"}},"SupplementalRequirements":{"EssayOrStatement":{"Value":"Required"},"Resume":{"Value":"Optional"},"Portfolio":{"Value":"Conditional"},"Interview":{"Value":"Conditional"},"AuditionOrPortfolioReview":{"Value":"Conditional"}}},"ApplicationRounds":[{"Name":"Early Action Fall 2026","Type":"Early Action","DueDate":{"Day":15,"Month":11},"Binding":false},{"Name":"Regular Decision Spring 2026","Type":"Regular Decision","DueDate":{"Day":1,"Month":12},"Binding":false},{"Name":"Regular Decision Fall 2026","Type":"Regular Decision","DueDate":{"Day":15,"Month":3},"Binding":false}]}