{"Scid":1100839,"Name":"University of Nebraska at Kearney","Address":"2504 9th Avenue","City":"Kearney","State":"NE","Zip":"68849-1212","WwwUrl":"http://www.unk.edu/","Opeid":"00255100","Opeid6":"002551","Iped":"181215","Setting":"Town","Location":{"type":"Point","coordinates":[-99.09870147705078,40.70145034790039]},"Country":"United States","ScoirApplyEnabled":false,"DisplayAsScoirApply":false,"CoalitionMember":false,"GeneralInfo":{"AdmPhone":"(308) 865-8526","AdmEmail":"","AdmFax":"308 865-8987","FinPhone":"308 865-8520","FtDegree3":4224,"HasOnCampusHousing":true,"HBCU":false,"HonorsCollege":"","OthRelig":"Not applicable","PublicPrivate":"Public","ResidenceCollege":true,"TotalDegree3":6017,"UnivType":"4 year","SchoolClassifier":"NotClassified"},"FreshEnroll":{"NumApplEnrolled":910,"NumApplOffered":6222,"NumApplReceived":7253},"TuitionAndExpenses":{"FeesIndistrict":1852,"FeesInstate":1852,"FeesOutstate":1842,"TuitionIndistrict":6450,"TuitionInstate":6450,"TuitionOutstate":12418,"RoomBoard":11936,"BookFees":770,"StickerInState":21008,"StickerOutState":26966},"AdmissionFreshmen":{"ApplicFeeAmt":45},"Admissions":{"CommonForm":"no","CoalitionForm":false,"CommonGroup":"no"},"FinancialAid":{"AverageDebt":20700,"DebtBalanceMedian":20700,"PcFedLoansReceived":40,"PcFinAidReceived":79},"NetPrice":{"NetAverage":16249,"Income1":13187,"Income2":13627,"Income3":14549,"Income4":18575,"Income5":20731},"CalculatedFields":{"AcceptanceRate":85.78519233420654,"SATMin":970,"SATMax":1150,"SATAvg":1060,"ACTAvg":21,"ACTMin":18,"ACTMax":25},"Sports":{},"Degrees":null,"ApplicationDetails":{"StandardizedTests":{"SATorACT":{"Value":"Optional"},"WithWriting":{"Value":"NotSpecified"},"SubjectTests":{"Value":"NotSpecified"}},"SupplementalRequirements":{"EssayOrStatement":{"Value":"NotSpecified"},"Resume":{"Value":"NotSpecified"},"Portfolio":{"Value":"NotSpecified"},"Interview":{"Value":"NotSpecified"},"AuditionOrPortfolioReview":{"Value":"NotSpecified"}}},"ApplicationRounds":[{"Name":"Rolling","Type":"Rolling","DueDate":{"Day":0,"Month":0},"Binding":false}]}