{"Scid":1100650,"Name":"Cornish College of the Arts","Address":"1000 Lenora Street","City":"Seattle","State":"WA","Zip":"98121","WwwUrl":"http://www.cornish.edu/","Opeid":"01231500","Opeid6":"012315","Iped":"235024","Setting":"City","Location":{"type":"Point","coordinates":[-122.33623504638672,47.6181755065918]},"Country":"United States","ScoirApplyEnabled":false,"DisplayAsScoirApply":false,"CoalitionMember":false,"GeneralInfo":{"AdmPhone":"(206) 726-5016","AdmEmail":"","AdmFax":"206 720-1011","FinPhone":"206 726-5014","FtDegree3":502,"HasOnCampusHousing":true,"HBCU":false,"HonorsCollege":"","OthRelig":"Not applicable","PublicPrivate":"Private - Not For-profit","ResidenceCollege":true,"TotalDegree3":502,"UnivType":"4 year","SchoolClassifier":"NotClassified"},"FreshEnroll":{"NumApplEnrolled":163,"NumApplOffered":773,"NumApplReceived":1097},"TuitionAndExpenses":{"FeesIndistrict":1597,"FeesInstate":1597,"FeesOutstate":1597,"TuitionIndistrict":38316,"TuitionInstate":38316,"TuitionOutstate":38316,"RoomBoard":15760,"BookFees":1800,"StickerInState":57473,"StickerOutState":57473},"AdmissionFreshmen":{"ApplicFeeAmt":60},"Admissions":{"CommonForm":"yes","CoalitionForm":false,"CommonGroup":"no"},"FinancialAid":{"AverageDebt":27000,"DebtBalanceMedian":27000,"PcFedLoansReceived":64,"PcFinAidReceived":93},"NetPrice":{"NetAverage":40164,"Income1":28155,"Income2":30948,"Income3":36693,"Income4":40853,"Income5":44405},"CalculatedFields":{"AcceptanceRate":70.46490428441203,"SATMin":0,"SATMax":0,"SATAvg":0,"ACTAvg":0,"ACTMin":0,"ACTMax":0},"Sports":{},"Degrees":null,"ApplicationDetails":{"StandardizedTests":{"SATorACT":{"Value":"NotRequired"},"WithWriting":{"Value":"NotSpecified"},"SubjectTests":{"Value":"NotSpecified"}},"SupplementalRequirements":{"EssayOrStatement":{"Value":"Required"},"Resume":{"Value":"Optional"},"Portfolio":{"Value":"Required"},"Interview":{"Value":"Optional"},"AuditionOrPortfolioReview":{"Value":"Required"}}},"ApplicationRounds":[{"Name":"Early Action Fall","Type":"Early Action","DueDate":{"Day":1,"Month":12},"Binding":false},{"Name":"Regular Decision Fall","Type":"Regular Decision","DueDate":{"Day":15,"Month":2},"Binding":false},{"Name":"Rolling Admission Fall","Type":"Rolling","DueDate":{"Day":30,"Month":6},"Binding":false}]}