{"Scid":2400016,"Name":"University of Arkansas","Address":"1125 W Maple St, Administration Bldg 425","City":"Fayetteville","State":"AR","Zip":"72701","WwwUrl":"https://www.uark.edu/","Opeid":"00110800","Opeid6":"001108","Iped":"106397","Setting":"City","Location":{"type":"Point","coordinates":[-94.1769790649414,36.07000732421875]},"Country":"United States","ScoirApplyEnabled":false,"DisplayAsScoirApply":false,"CoalitionMember":false,"GeneralInfo":{"AdmPhone":"(479) 575-5346","AdmEmail":"","AdmFax":"479 575-7515","FinPhone":"479 575-3806","FtDegree3":27472,"HasOnCampusHousing":true,"HBCU":false,"HonorsCollege":"Invite","OthRelig":"Not applicable","PublicPrivate":"Public","ResidenceCollege":true,"TotalDegree3":32140,"UnivType":"4 year","SchoolClassifier":"NotClassified"},"FreshEnroll":{"NumApplEnrolled":6337,"NumApplOffered":20202,"NumApplReceived":28186},"TuitionAndExpenses":{"FeesIndistrict":2082,"FeesInstate":2082,"FeesOutstate":2082,"TuitionIndistrict":7666,"TuitionInstate":7666,"TuitionOutstate":26690,"RoomBoard":13290,"BookFees":1154,"StickerInState":24192,"StickerOutState":43216},"AdmissionFreshmen":{"ApplicFeeAmt":40},"Admissions":{"CommonForm":"yes","CoalitionForm":false,"CommonGroup":"no"},"FinancialAid":{"AverageDebt":21500,"DebtBalanceMedian":21500,"PcFedLoansReceived":33,"PcFinAidReceived":52},"NetPrice":{"NetAverage":17475,"Income1":13017,"Income2":14115,"Income3":17379,"Income4":19755,"Income5":20991},"CalculatedFields":{"AcceptanceRate":71.67388064996807,"SATMin":1050,"SATMax":1220,"SATAvg":1135,"ACTAvg":24,"ACTMin":21,"ACTMax":28},"Sports":{},"Degrees":null,"ApplicationDetails":{"StandardizedTests":{"SATorACT":{"Value":"Conditional"},"WithWriting":{"Value":"NotSpecified"},"SubjectTests":{"Value":"NotSpecified"}},"SupplementalRequirements":{"EssayOrStatement":{"Value":"Conditional"},"Resume":{"Value":"Conditional"},"Portfolio":{"Value":"NotRequired"},"Interview":{"Value":"NotRequired"},"AuditionOrPortfolioReview":{"Value":"NotRequired"}}},"ApplicationRounds":[{"Name":"Rolling","Type":"Rolling","DueDate":{"Day":1,"Month":8},"Binding":false},{"Name":"Priority","Type":"Priority","DueDate":{"Day":1,"Month":11},"Binding":false}]}