{"Scid":2400200,"Name":"North Carolina A \u0026 T State University","Address":"1601 E Market  St","City":"Greensboro","State":"NC","Zip":"27411","WwwUrl":"http://www.ncat.edu/","Opeid":"00290500","Opeid6":"002905","Iped":"199102","Setting":"City","Location":{"type":"Point","coordinates":[-79.77337646484375,36.072818756103516]},"Country":"United States","ScoirApplyEnabled":false,"DisplayAsScoirApply":false,"CoalitionMember":false,"GeneralInfo":{"AdmPhone":"(336) 334-7946","AdmEmail":"uadmit@ncat.edu","AdmFax":"336 334-7478","FinPhone":"336 334-7973","FtDegree3":12216,"HasOnCampusHousing":true,"HBCU":true,"HonorsCollege":"","OthRelig":"Not applicable","PublicPrivate":"Public","ResidenceCollege":true,"TotalDegree3":13885,"UnivType":"4 year","SchoolClassifier":"NotClassified"},"FreshEnroll":{"NumApplEnrolled":2755,"NumApplOffered":14183,"NumApplReceived":30717},"TuitionAndExpenses":{"FeesIndistrict":3208,"FeesInstate":3208,"FeesOutstate":3208,"TuitionIndistrict":3540,"TuitionInstate":3540,"TuitionOutstate":17200,"RoomBoard":8832,"BookFees":1500,"StickerInState":17080,"StickerOutState":30740},"AdmissionFreshmen":{"ApplicFeeAmt":60},"Admissions":{"CommonForm":"yes","CoalitionForm":false,"CommonGroup":"no"},"FinancialAid":{"AverageDebt":28500,"DebtBalanceMedian":28500,"PcFedLoansReceived":66,"PcFinAidReceived":83},"NetPrice":{"NetAverage":10258,"Income1":7314,"Income2":8701,"Income3":13024,"Income4":17075,"Income5":18685},"CalculatedFields":{"AcceptanceRate":46.173128886284466,"SATMin":960,"SATMax":1190,"SATAvg":1075,"ACTAvg":19,"ACTMin":16,"ACTMax":22},"Sports":{},"Degrees":null,"ApplicationDetails":{"StandardizedTests":{"SATorACT":{"Value":"Optional"},"WithWriting":{"Value":"NotSpecified"},"SubjectTests":{"Value":"NotSpecified"}},"SupplementalRequirements":{"EssayOrStatement":{"Value":"NotRequired"},"Resume":{"Value":"NotRequired"},"Portfolio":{"Value":"NotRequired"},"Interview":{"Value":"NotRequired"},"AuditionOrPortfolioReview":{"Value":"NotRequired"}}},"ApplicationRounds":[{"Name":"Early Action","Type":"Early Action","DueDate":{"Day":1,"Month":11},"Binding":false},{"Name":"Regular Decision","Type":"Regular Decision","DueDate":{"Day":1,"Month":2},"Binding":false},{"Name":"Rolling","Type":"Rolling","DueDate":{"Day":0,"Month":0},"Binding":false},{"Name":"Rolling (starts after RD deadline)","Type":"Rolling","DueDate":{"Day":0,"Month":0},"Binding":false}]}