{"Scid":2400007,"Name":"Albany State University","Address":"504 College Drive","City":"Albany","State":"GA","Zip":"31705","WwwUrl":"https://www.asurams.edu/","Opeid":"00154400","Opeid6":"001544","Iped":"138716","Setting":"City","Location":{"type":"Point","coordinates":[-84.1418228149414,31.56928062438965]},"Country":"United States","ScoirApplyEnabled":false,"DisplayAsScoirApply":false,"CoalitionMember":false,"GeneralInfo":{"AdmPhone":"(229) 430-4646","AdmEmail":"admissions@asurams.edu","AdmFax":"229 430-4105","FinPhone":"229 430-4650","FtDegree3":6018,"HasOnCampusHousing":true,"HBCU":true,"HonorsCollege":"","OthRelig":"Not applicable","PublicPrivate":"Public","ResidenceCollege":true,"TotalDegree3":6544,"UnivType":"4 year","SchoolClassifier":"NotClassified"},"FreshEnroll":{},"TuitionAndExpenses":{"FeesIndistrict":1870,"FeesInstate":1870,"FeesOutstate":1870,"TuitionIndistrict":4064,"TuitionInstate":4064,"TuitionOutstate":14786,"RoomBoard":9066,"BookFees":1220,"StickerInState":16220,"StickerOutState":26942},"AdmissionFreshmen":{"ApplicFeeAmt":25},"Admissions":{"CommonForm":"no","CoalitionForm":false,"CommonGroup":"no"},"FinancialAid":{"AverageDebt":32555,"DebtBalanceMedian":32555,"PcFedLoansReceived":60,"PcFinAidReceived":99},"NetPrice":{"NetAverage":13775,"Income1":12993,"Income2":13402,"Income3":16225,"Income4":18897,"Income5":19054},"CalculatedFields":{"AcceptanceRate":-1,"SATMin":0,"SATMax":0,"SATAvg":0,"ACTAvg":0,"ACTMin":0,"ACTMax":0},"Sports":{},"Degrees":null,"ApplicationDetails":{"StandardizedTests":{"SATorACT":{"Value":"Required"},"WithWriting":{"Value":"NotSpecified"},"SubjectTests":{"Value":"NotSpecified"}},"SupplementalRequirements":{"EssayOrStatement":{"Value":"NotSpecified"},"Resume":{"Value":"NotSpecified"},"Portfolio":{"Value":"NotSpecified"},"Interview":{"Value":"NotSpecified"},"AuditionOrPortfolioReview":{"Value":"NotSpecified"}}},"ApplicationRounds":[{"Name":"Priority","Type":"Priority","DueDate":{"Day":1,"Month":4},"Binding":false},{"Name":"Rolling","Type":"Rolling","DueDate":{"Day":0,"Month":0},"Binding":false}]}