{"Scid":2600034,"Name":"University of Virginia (Main Campus)","Address":"1827 University Avenue","City":"Charlottesville","State":"VA","Zip":"22903-2628","WwwUrl":"https://www.virginia.edu/","Opeid":"00374500","Opeid6":"003745","Iped":"234076","Setting":"Suburban","Location":{"type":"Point","coordinates":[-78.50342559814453,38.03566360473633]},"Country":"United States","VerifiedByDataOwner":true,"ScoirApplyEnabled":false,"DisplayAsScoirApply":false,"CoalitionMember":false,"GeneralInfo":{"AdmPhone":"(434) 982-3200","AdmEmail":"undergradadmission@virginia.edu","AdmFax":"434 924-3587","FinPhone":"434 982-6000","FtDegree3":17612,"HasOnCampusHousing":true,"HBCU":false,"HonorsCollege":"","OthRelig":"Not applicable","PublicPrivate":"Public","ResidenceCollege":true,"TotalDegree3":25924,"UnivType":"4 year","SchoolClassifier":"NotClassified"},"FreshEnroll":{"NumApplEnrolled":3966,"NumApplOffered":9533,"NumApplReceived":56528},"TuitionAndExpenses":{"FeesIndistrict":3496,"FeesInstate":3496,"FeesOutstate":4178,"TuitionIndistrict":17490,"TuitionInstate":17490,"TuitionOutstate":53836,"RoomBoard":13940,"BookFees":1480,"StickerInState":36406,"StickerOutState":73434},"AdmissionFreshmen":{"ApplicFeeAmt":75},"Admissions":{"CommonForm":"yes","CoalitionForm":false,"CommonGroup":"yes"},"FinancialAid":{"AverageDebt":19633,"DebtBalanceMedian":26211,"PcFedLoansReceived":22,"PcFinAidReceived":42},"NetPrice":{"NetAverage":17831,"Income1":10123,"Income2":8842,"Income3":14658,"Income4":24023,"Income5":34777},"CalculatedFields":{"AcceptanceRate":16.86420888763091,"SATMin":1410,"SATMax":1530,"SATAvg":1470,"ACTAvg":33,"ACTMin":32,"ACTMax":34},"Sports":{},"Degrees":null,"ApplicationDetails":{"StandardizedTests":{"SATorACT":{"Value":"Optional"},"WithWriting":{"Value":"NotSpecified"},"SubjectTests":{"Value":"NotSpecified"}},"SupplementalRequirements":{"EssayOrStatement":{"Value":"Required"},"Resume":{"Value":"NotRequired"},"Portfolio":{"Value":"Optional"},"Interview":{"Value":"NotRequired"},"AuditionOrPortfolioReview":{"Value":"NotRequired"}}},"ApplicationRounds":[{"Name":"Early Action Fall 2026","Type":"Early Action","DueDate":{"Day":1,"Month":11},"Binding":false},{"Name":"Early Decision Fall 2026","Type":"Early Decision","DueDate":{"Day":1,"Month":11},"Binding":true},{"Name":"Regular Decision Fall 2026","Type":"Regular Decision","DueDate":{"Day":5,"Month":1},"Binding":false}]}