{"Scid":2600114,"Name":"University of South Alabama","Address":"307 N University Blvd","City":"Mobile","State":"AL","Zip":"36688-0002","WwwUrl":"http://www.southalabama.edu/","Opeid":"00105700","Opeid6":"001057","Iped":"102094","Setting":"City","Location":{"type":"Point","coordinates":[-88.1787109375,30.696033477783203]},"Country":"United States","ScoirApplyEnabled":false,"DisplayAsScoirApply":false,"CoalitionMember":false,"GeneralInfo":{"AdmPhone":"(251) 460-6141","AdmEmail":"admiss@southalabama.edu","AdmFax":"251 460-7876","FinPhone":"800 305-6828","FtDegree3":8914,"HasOnCampusHousing":true,"HBCU":false,"HonorsCollege":"","OthRelig":"Not applicable","PublicPrivate":"Public","ResidenceCollege":true,"TotalDegree3":13768,"UnivType":"4 year","SchoolClassifier":"NotClassified"},"FreshEnroll":{"NumApplEnrolled":1920,"NumApplOffered":8247,"NumApplReceived":12593},"TuitionAndExpenses":{"FeesIndistrict":700,"FeesInstate":700,"FeesOutstate":700,"TuitionIndistrict":8976,"TuitionInstate":8976,"TuitionOutstate":17952,"RoomBoard":8830,"BookFees":2020,"StickerInState":20526,"StickerOutState":29502},"AdmissionFreshmen":{"ApplicFeeAmt":35},"Admissions":{"CommonForm":"yes","CoalitionForm":false,"CommonGroup":"no"},"FinancialAid":{"AverageDebt":24711,"DebtBalanceMedian":24711,"PcFedLoansReceived":51,"PcFinAidReceived":75},"NetPrice":{"NetAverage":13613,"Income1":10148,"Income2":11633,"Income3":15456,"Income4":21143,"Income5":21878},"CalculatedFields":{"AcceptanceRate":65.48876359882475,"SATMin":1015,"SATMax":1200,"SATAvg":1107,"ACTAvg":22,"ACTMin":19,"ACTMax":26},"Sports":{},"Degrees":null,"ApplicationDetails":{"StandardizedTests":{"SATorACT":{"Value":"Optional"},"WithWriting":{"Value":"NotRequired"},"SubjectTests":{"Value":"NotSpecified"}},"SupplementalRequirements":{"EssayOrStatement":{"Value":"NotSpecified"},"Resume":{"Value":"Optional"},"Portfolio":{"Value":"NotSpecified"},"Interview":{"Value":"NotSpecified"},"AuditionOrPortfolioReview":{"Value":"NotSpecified"}}},"ApplicationRounds":[{"Name":"Rolling Admission Spring Semester 2026","Type":"Rolling","DueDate":{"Day":1,"Month":12},"Binding":false},{"Name":"Rolling Admission Summer Semester 2026","Type":"Rolling","DueDate":{"Day":1,"Month":5},"Binding":false},{"Name":"Rolling Admission Fall Semester 2026","Type":"Rolling","DueDate":{"Day":15,"Month":7},"Binding":false}]}