{"Scid":3000171,"Name":"Amridge University","Address":"1200 Taylor Rd","City":"Montgomery","State":"AL","Zip":"36117-3553","WwwUrl":"https://www.amridgeuniversity.edu/","Opeid":"02503400","Opeid6":"025034","Iped":"100690","Setting":"City","Location":{"type":"Point","coordinates":[-86.17401123046875,32.36260986328125]},"Country":"United States","ScoirApplyEnabled":false,"DisplayAsScoirApply":false,"CoalitionMember":false,"GeneralInfo":{"AdmPhone":"(800) 351-4040","AdmEmail":"","AdmFax":"334 387-3878","FinPhone":"800 351-4040","FtDegree3":226,"HBCU":false,"HonorsCollege":"","OthRelig":"Christian - other","PublicPrivate":"Private - Not For-profit","TotalDegree3":636,"UnivType":"4 year","SchoolClassifier":"NotClassified"},"FreshEnroll":{},"TuitionAndExpenses":{"FeesIndistrict":0,"FeesInstate":0,"FeesOutstate":0,"TuitionIndistrict":0,"TuitionInstate":0,"TuitionOutstate":0,"RoomBoard":0,"BookFees":0,"StickerInState":0,"StickerOutState":0},"AdmissionFreshmen":{"ApplicFeeAmt":50},"Admissions":{"CommonForm":"no","CoalitionForm":false,"CommonGroup":"no"},"FinancialAid":{"AverageDebt":23370,"DebtBalanceMedian":23370,"PcFedLoansReceived":84,"PcFinAidReceived":95},"NetPrice":{"NetAverage":0,"Income1":0,"Income2":0,"Income3":0,"Income4":0,"Income5":0},"CalculatedFields":{"AcceptanceRate":-1,"SATMin":0,"SATMax":0,"SATAvg":0,"ACTAvg":0,"ACTMin":0,"ACTMax":0},"Sports":{},"Degrees":null,"ApplicationDetails":{"StandardizedTests":{"SATorACT":{"Value":"Required"},"WithWriting":{"Value":"NotRequired"},"SubjectTests":{"Value":"NotSpecified"}},"SupplementalRequirements":{"EssayOrStatement":{"Value":"NotSpecified"},"Resume":{"Value":"NotSpecified"},"Portfolio":{"Value":"NotSpecified"},"Interview":{"Value":"NotSpecified"},"AuditionOrPortfolioReview":{"Value":"NotSpecified"}}},"ApplicationRounds":[{"Name":"Rolling","Type":"Rolling","DueDate":{"Day":0,"Month":0},"Binding":false}]}