{"Scid":4000855,"Name":"Holy Cross College","Address":"54515 State Road 933 North","City":"Notre Dame","State":"IN","Zip":"46556-0308","WwwUrl":"http://www.hcc-nd.edu/","Opeid":"00726300","Opeid6":"007263","Iped":"150774","Setting":"Suburban","Location":{"type":"Point","coordinates":[-86.25382232666016,41.698997497558594]},"Country":"United States","ScoirApplyEnabled":false,"DisplayAsScoirApply":false,"CoalitionMember":false,"GeneralInfo":{"AdmPhone":"(574) 239-8400","AdmEmail":"admissions@hcc-nd.edu","AdmFax":"574 239-8323","FinPhone":"574 239-8408","FtDegree3":547,"HasOnCampusHousing":true,"HBCU":false,"HonorsCollege":"","OthRelig":"Catholic","PublicPrivate":"Private - Not For-profit","ResidenceCollege":true,"TotalDegree3":547,"UnivType":"4 year","SchoolClassifier":"NotClassified"},"FreshEnroll":{"NumApplEnrolled":250,"NumApplOffered":1231,"NumApplReceived":1670},"TuitionAndExpenses":{"FeesIndistrict":1400,"FeesInstate":1400,"FeesOutstate":1400,"TuitionIndistrict":34100,"TuitionInstate":34100,"TuitionOutstate":34100,"RoomBoard":12300,"BookFees":1100,"StickerInState":48900,"StickerOutState":48900},"AdmissionFreshmen":{"ApplicFeeAmt":0},"Admissions":{"CommonForm":"yes","CoalitionForm":false,"CommonGroup":"no"},"FinancialAid":{"AverageDebt":25000,"DebtBalanceMedian":25000,"PcFedLoansReceived":63,"PcFinAidReceived":82},"NetPrice":{"NetAverage":24214,"Income1":13969,"Income2":15859,"Income3":18845,"Income4":24241,"Income5":33940},"CalculatedFields":{"AcceptanceRate":73.7125748502994,"SATMin":980,"SATMax":1300,"SATAvg":1140,"ACTAvg":28,"ACTMin":23,"ACTMax":31},"Sports":{},"Degrees":null,"ApplicationDetails":{"StandardizedTests":{"SATorACT":{"Value":"Optional"},"WithWriting":{"Value":"NotSpecified"},"SubjectTests":{"Value":"NotSpecified"}},"SupplementalRequirements":{"EssayOrStatement":{"Value":"Required"},"Resume":{"Value":"Optional"},"Portfolio":{"Value":"NotRequired"},"Interview":{"Value":"Conditional"},"AuditionOrPortfolioReview":{"Value":"NotRequired"}}},"ApplicationRounds":[{"Name":"Early Action","Type":"Early Action","DueDate":{"Day":1,"Month":11},"Binding":false},{"Name":"Regular Decision","Type":"Regular Decision","DueDate":{"Day":15,"Month":2},"Binding":false},{"Name":"Rolling Admissions Continues","Type":"Other","DueDate":{"Day":28,"Month":7},"Binding":false}]}