{"Scid":4001093,"Name":"Young Harris College","Address":"1 College Street","City":"Young Harris","State":"GA","Zip":"30582","WwwUrl":"http://www.yhc.edu/","Opeid":"00160400","Opeid6":"001604","Iped":"141361","Setting":"Rural","Location":{"type":"Point","coordinates":[-83.84587097167969,34.93352127075195]},"Country":"United States","VerifiedByDataOwner":true,"ScoirApplyEnabled":false,"DisplayAsScoirApply":false,"CoalitionMember":false,"GeneralInfo":{"AdmPhone":"(706) 379-3111","AdmEmail":"admissions@yhc.edu","AdmFax":"706 379-3108","FinPhone":"706 379-5162","FtDegree3":1403,"HasOnCampusHousing":true,"HBCU":false,"HonorsCollege":"","OthRelig":"Methodist","PublicPrivate":"Private - Not For-profit","ResidenceCollege":true,"TotalDegree3":1420,"UnivType":"4 year","SchoolClassifier":"NotClassified"},"FreshEnroll":{"NumApplEnrolled":242,"NumApplOffered":1233,"NumApplReceived":1926},"TuitionAndExpenses":{"FeesIndistrict":1505,"FeesInstate":1505,"FeesOutstate":1505,"TuitionIndistrict":30800,"TuitionInstate":30800,"TuitionOutstate":30800,"RoomBoard":13000,"BookFees":0,"StickerInState":45305,"StickerOutState":45305},"AdmissionFreshmen":{"ApplicFeeAmt":0},"Admissions":{"CommonForm":"no","CoalitionForm":false,"CommonGroup":"no"},"FinancialAid":{"AverageDebt":26000,"DebtBalanceMedian":26000,"PcFedLoansReceived":40,"PcFinAidReceived":100},"NetPrice":{"NetAverage":20509,"Income1":11154,"Income2":7888,"Income3":9309,"Income4":13219,"Income5":12588},"CalculatedFields":{"AcceptanceRate":64.01869158878505,"SATMin":0,"SATMax":0,"SATAvg":0,"ACTAvg":0,"ACTMin":0,"ACTMax":0},"Sports":{},"Degrees":null,"ApplicationDetails":{"StandardizedTests":{"SATorACT":{"Value":"Optional"},"WithWriting":{"Value":"NotSpecified"},"SubjectTests":{"Value":"NotSpecified"}},"SupplementalRequirements":{"EssayOrStatement":{"Value":"NotSpecified"},"Resume":{"Value":"NotSpecified"},"Portfolio":{"Value":"NotSpecified"},"Interview":{"Value":"NotSpecified"},"AuditionOrPortfolioReview":{"Value":"NotSpecified"}}},"ApplicationRounds":[{"Name":"Rolling","Type":"Rolling","DueDate":{"Day":0,"Month":0},"Binding":false}]}