{"Scid":5000184,"Name":"Pacific Islands University","Address":"172 Kinney's Road","City":"Mangilao","State":"GU","Zip":"96913-5917","WwwUrl":"http://www.piu.edu/","Opeid":"03438300","Opeid6":"034383","Iped":"439862","Setting":"Suburban","Location":{"type":"Point","coordinates":[144.8358154296875,13.465045928955078]},"Country":"Guam","ScoirApplyEnabled":false,"DisplayAsScoirApply":false,"CoalitionMember":false,"GeneralInfo":{"AdmPhone":"#N/A","AdmEmail":"","AdmFax":"","FinPhone":"","FtDegree3":55,"HasOnCampusHousing":true,"HBCU":false,"HonorsCollege":"","OthRelig":"Christian - other","PublicPrivate":"Private - Not For-profit","ResidenceCollege":true,"TotalDegree3":55,"UnivType":"4 year","SchoolClassifier":"NotClassified"},"FreshEnroll":{"NumApplEnrolled":7,"NumApplOffered":28,"NumApplReceived":71},"TuitionAndExpenses":{"FeesIndistrict":650,"FeesInstate":650,"FeesOutstate":650,"TuitionIndistrict":6553,"TuitionInstate":6553,"TuitionOutstate":6553,"RoomBoard":4564,"BookFees":300,"StickerInState":12067,"StickerOutState":12067},"AdmissionFreshmen":{"ApplicFeeAmt":25},"Admissions":{"CommonForm":"no","CoalitionForm":false,"CommonGroup":""},"FinancialAid":{"AverageDebt":0,"DebtBalanceMedian":0,"PcFedLoansReceived":66,"PcFinAidReceived":35},"NetPrice":{"NetAverage":5873,"Income1":6746,"Income2":0,"Income3":0,"Income4":0,"Income5":0},"CalculatedFields":{"AcceptanceRate":39.436619718309856,"SATMin":0,"SATMax":0,"SATAvg":0,"ACTAvg":0,"ACTMin":0,"ACTMax":0},"Sports":{},"Degrees":null,"ApplicationDetails":{"StandardizedTests":{"SATorACT":{"Value":"Required"},"WithWriting":{"Value":"NotSpecified"},"SubjectTests":{"Value":"NotSpecified"}},"SupplementalRequirements":{"EssayOrStatement":{"Value":"NotSpecified"},"Resume":{"Value":"NotSpecified"},"Portfolio":{"Value":"NotSpecified"},"Interview":{"Value":"NotSpecified"},"AuditionOrPortfolioReview":{"Value":"NotSpecified"}}},"ApplicationRounds":[{"Name":"Rolling","Type":"Rolling","DueDate":{"Day":0,"Month":0},"Binding":false}]}