{"Scid":6000161,"Name":"Forman Christian College","Address":"Zahoor Elahi Road","City":"Lahore","Zip":"54600","WwwUrl":"http://www.fccollege.edu.pk/","Location":{"type":"Point","coordinates":[74.33505249023438,31.525981903076172]},"Country":"Pakistan","ScoirApplyEnabled":false,"DisplayAsScoirApply":false,"CoalitionMember":false,"GeneralInfo":{"AdmPhone":"","AdmEmail":"","AdmFax":"","FinPhone":"","FtDegree3":0,"HBCU":false,"HonorsCollege":"","OthRelig":"Not applicable","PublicPrivate":"Private - Not For-profit","TotalDegree3":6347,"UnivType":"","SchoolClassifier":"NotClassified"},"FreshEnroll":{},"TuitionAndExpenses":{"FeesIndistrict":0,"FeesInstate":0,"FeesOutstate":0,"TuitionIndistrict":944,"TuitionInstate":944,"TuitionOutstate":944,"RoomBoard":0,"BookFees":0,"StickerInState":944,"StickerOutState":944},"AdmissionFreshmen":{"ApplicFeeAmt":138.76},"Admissions":{"CommonForm":"no","CoalitionForm":false,"CommonGroup":""},"FinancialAid":{"AverageDebt":0,"DebtBalanceMedian":0},"NetPrice":{"NetAverage":0,"Income1":0,"Income2":0,"Income3":0,"Income4":0,"Income5":0},"CalculatedFields":{"AcceptanceRate":-1,"SATMin":0,"SATMax":0,"SATAvg":0,"ACTAvg":0,"ACTMin":0,"ACTMax":0},"Sports":{},"Degrees":null,"ApplicationDetails":{"StandardizedTests":{"SATorACT":{"Value":"NotSpecified"},"WithWriting":{"Value":"NotSpecified"},"SubjectTests":{"Value":"Required"}},"SupplementalRequirements":{"EssayOrStatement":{"Value":"NotSpecified"},"Resume":{"Value":"NotSpecified"},"Portfolio":{"Value":"NotSpecified"},"Interview":{"Value":"NotSpecified"},"AuditionOrPortfolioReview":{"Value":"NotSpecified"}}},"ApplicationRounds":[{"Name":"Regular Decision","Type":"Regular Decision","DueDate":{"Day":17,"Month":7},"Binding":false}]}