{"Scid":6000200,"Name":"Brunel University London","Address":"Kingston Ln","City":"London","State":"England","Zip":"UB8 3PH","WwwUrl":"http://www.brunel.ac.uk/","Setting":"Suburban","Location":{"type":"Point","coordinates":[-0.4713994860649109,51.53315734863281]},"Country":"England","VerifiedByDataOwner":true,"ScoirApplyEnabled":false,"DisplayAsScoirApply":false,"CoalitionMember":false,"GeneralInfo":{"AdmPhone":"","AdmEmail":"admissions@brunel.ac.uk","AdmFax":"","FinPhone":"","FtDegree3":11890,"HasOnCampusHousing":true,"HBCU":false,"HonorsCollege":"","OthRelig":"Not applicable","PublicPrivate":"Public","TotalDegree3":18655,"UnivType":"4 year","SchoolClassifier":"NotClassified"},"FreshEnroll":{"NumApplEnrolled":172,"NumApplOffered":2051,"NumApplReceived":3100},"TuitionAndExpenses":{"FeesIndistrict":0,"FeesInstate":0,"FeesOutstate":0,"TuitionIndistrict":19500,"TuitionInstate":19500,"TuitionOutstate":19500,"RoomBoard":10000,"BookFees":0,"StickerInState":29500,"StickerOutState":29500},"AdmissionFreshmen":{"ApplicFeeAmt":0},"Admissions":{"CommonForm":"yes","CoalitionForm":false,"CommonGroup":""},"FinancialAid":{"AverageDebt":0,"DebtBalanceMedian":0},"NetPrice":{"NetAverage":0,"Income1":0,"Income2":0,"Income3":0,"Income4":0,"Income5":0},"CalculatedFields":{"AcceptanceRate":66.16129032258064,"SATMin":0,"SATMax":0,"SATAvg":0,"ACTAvg":0,"ACTMin":0,"ACTMax":0},"Sports":{},"Degrees":null,"ApplicationDetails":{"StandardizedTests":{"SATorACT":{"Value":"Optional"},"WithWriting":{"Value":"Required"},"SubjectTests":{"Value":"Required"}},"SupplementalRequirements":{"EssayOrStatement":{"Value":"Required"},"Resume":{"Value":"NotSpecified"},"Portfolio":{"Value":"NotSpecified"},"Interview":{"Value":"NotSpecified"},"AuditionOrPortfolioReview":{"Value":"NotSpecified"}}},"ApplicationRounds":[{"Name":"Rolling","Type":"Rolling","DueDate":{"Day":0,"Month":0},"Binding":false}]}