{"Scid":7000565,"Name":"Muskegon Community College","Address":"221 S Quarterline Rd","City":"Muskegon","State":"MI","Zip":"49442-1432","WwwUrl":"http://www.muskegoncc.edu/","Opeid":"00229700","Opeid6":"002297","Iped":"171304","Setting":"City","Location":{"type":"Point","coordinates":[-86.19638061523438,43.250328063964844]},"Country":"United States","ScoirApplyEnabled":false,"DisplayAsScoirApply":false,"CoalitionMember":false,"GeneralInfo":{"AdmPhone":"#N/A","AdmEmail":"","AdmFax":"","FinPhone":"","FtDegree3":3518,"HBCU":false,"HonorsCollege":"","OthRelig":"Not applicable","PublicPrivate":"Public","TotalDegree3":3518,"UnivType":"2 year","SchoolClassifier":"NotClassified"},"FreshEnroll":{},"TuitionAndExpenses":{"FeesIndistrict":1790,"FeesInstate":1790,"FeesOutstate":1790,"TuitionIndistrict":5200,"TuitionInstate":9720,"TuitionOutstate":13600,"RoomBoard":5380,"BookFees":1150,"StickerInState":18040,"StickerOutState":21920},"AdmissionFreshmen":{"ApplicFeeAmt":0},"Admissions":{"CommonForm":"no","CoalitionForm":false,"CommonGroup":""},"FinancialAid":{"AverageDebt":8424.5,"DebtBalanceMedian":8424,"PcFedLoansReceived":6,"PcFinAidReceived":99},"NetPrice":{"NetAverage":7829,"Income1":3903,"Income2":4534,"Income3":7577,"Income4":7512,"Income5":4958},"CalculatedFields":{"AcceptanceRate":-1,"SATMin":0,"SATMax":0,"SATAvg":0,"ACTAvg":0,"ACTMin":0,"ACTMax":0},"Sports":{},"Degrees":null,"ApplicationDetails":{"StandardizedTests":{"SATorACT":{"Value":"NotRequired"},"WithWriting":{"Value":"NotRequired"},"SubjectTests":{"Value":"NotRequired"}},"SupplementalRequirements":{"EssayOrStatement":{"Value":"NotRequired"},"Resume":{"Value":"NotRequired"},"Portfolio":{"Value":"NotRequired"},"Interview":{"Value":"NotRequired"},"AuditionOrPortfolioReview":{"Value":"NotRequired"}}},"ApplicationRounds":[{"Name":"Rolling","Type":"Rolling","DueDate":{"Day":0,"Month":0},"Binding":false}]}