{"Scid":7000931,"Name":"Midlands Technical College","Address":"1260 Lexington Drive","City":"West Columbia","State":"SC","Zip":"29170-2176","WwwUrl":"https://www.midlandstech.edu/","Opeid":"00399300","Opeid6":"003993","Iped":"218353","Setting":"Suburban","Location":{"type":"Point","coordinates":[-81.11576080322266,33.94932556152344]},"Country":"United States","ScoirApplyEnabled":false,"DisplayAsScoirApply":false,"CoalitionMember":false,"GeneralInfo":{"AdmPhone":"#N/A","AdmEmail":"","AdmFax":"","FinPhone":"","FtDegree3":8978,"HBCU":false,"HonorsCollege":"","OthRelig":"Not applicable","PublicPrivate":"Public","TotalDegree3":8978,"UnivType":"2 year","SchoolClassifier":"NotClassified"},"FreshEnroll":{},"TuitionAndExpenses":{"FeesIndistrict":276,"FeesInstate":276,"FeesOutstate":276,"TuitionIndistrict":4512,"TuitionInstate":5640,"TuitionOutstate":13536,"RoomBoard":13457,"BookFees":1578,"StickerInState":20951,"StickerOutState":28847},"AdmissionFreshmen":{"ApplicFeeAmt":35},"Admissions":{"CommonForm":"no","CoalitionForm":false,"CommonGroup":""},"FinancialAid":{"AverageDebt":10750,"DebtBalanceMedian":10750,"PcFedLoansReceived":22,"PcFinAidReceived":93},"NetPrice":{"NetAverage":5433,"Income1":4839,"Income2":3522,"Income3":6031,"Income4":6717,"Income5":6552},"CalculatedFields":{"AcceptanceRate":-1,"SATMin":0,"SATMax":0,"SATAvg":0,"ACTAvg":0,"ACTMin":0,"ACTMax":0},"Sports":{},"Degrees":null,"ApplicationDetails":{"StandardizedTests":{"SATorACT":{"Value":"NotRequired"},"WithWriting":{"Value":"NotRequired"},"SubjectTests":{"Value":"NotRequired"}},"SupplementalRequirements":{"EssayOrStatement":{"Value":"NotRequired"},"Resume":{"Value":"NotRequired"},"Portfolio":{"Value":"NotRequired"},"Interview":{"Value":"NotRequired"},"AuditionOrPortfolioReview":{"Value":"NotRequired"}}},"ApplicationRounds":[{"Name":"Rolling","Type":"Rolling","DueDate":{"Day":0,"Month":0},"Binding":false}]}