{"Scid":7000553,"Name":"Grand Rapids Community College","Address":"143 Bostwick Ave NE","City":"Grand Rapids","State":"MI","Zip":"49503-3295","WwwUrl":"https://www.grcc.edu/","Opeid":"00226700","Opeid6":"002267","Iped":"170055","Setting":"City","Location":{"type":"Point","coordinates":[-85.6656265258789,42.96707534790039]},"Country":"United States","ScoirApplyEnabled":false,"DisplayAsScoirApply":false,"CoalitionMember":false,"GeneralInfo":{"AdmPhone":"#N/A","AdmEmail":"","AdmFax":"","FinPhone":"","FtDegree3":12142,"HBCU":false,"HonorsCollege":"","OthRelig":"Not applicable","PublicPrivate":"Public","TotalDegree3":12142,"UnivType":"2 year","SchoolClassifier":"NotClassified"},"FreshEnroll":{},"TuitionAndExpenses":{"FeesIndistrict":459,"FeesInstate":459,"FeesOutstate":459,"TuitionIndistrict":3600,"TuitionInstate":7590,"TuitionOutstate":11400,"RoomBoard":8679,"BookFees":616,"StickerInState":17344,"StickerOutState":21154},"AdmissionFreshmen":{"ApplicFeeAmt":0},"Admissions":{"CommonForm":"no","CoalitionForm":false,"CommonGroup":""},"FinancialAid":{"AverageDebt":10370.5,"DebtBalanceMedian":10370,"PcFedLoansReceived":15,"PcFinAidReceived":55},"NetPrice":{"NetAverage":11137,"Income1":9228,"Income2":9706,"Income3":12201,"Income4":14418,"Income5":15347},"CalculatedFields":{"AcceptanceRate":-1,"SATMin":0,"SATMax":0,"SATAvg":0,"ACTAvg":0,"ACTMin":0,"ACTMax":0},"Sports":{},"Degrees":null,"ApplicationDetails":{"StandardizedTests":{"SATorACT":{"Value":"NotRequired"},"WithWriting":{"Value":"NotRequired"},"SubjectTests":{"Value":"NotRequired"}},"SupplementalRequirements":{"EssayOrStatement":{"Value":"NotRequired"},"Resume":{"Value":"NotRequired"},"Portfolio":{"Value":"NotRequired"},"Interview":{"Value":"NotRequired"},"AuditionOrPortfolioReview":{"Value":"NotRequired"}}},"ApplicationRounds":[{"Name":"Rolling","Type":"Rolling","DueDate":{"Day":0,"Month":0},"Binding":false}]}