{"Scid":7001084,"Name":"South Puget Sound Community College","Address":"2011 Mottman Rd SW","City":"Olympia","State":"WA","Zip":"98512-6292","WwwUrl":"http://www.spscc.edu/","Opeid":"00537200","Opeid6":"005372","Iped":"236656","Setting":"City","Location":{"type":"Point","coordinates":[-122.92958068847656,47.02369689941406]},"Country":"United States","ScoirApplyEnabled":false,"DisplayAsScoirApply":false,"CoalitionMember":false,"GeneralInfo":{"AdmPhone":"#N/A","AdmEmail":"","AdmFax":"","FinPhone":"","FtDegree3":4252,"HBCU":false,"HonorsCollege":"","OthRelig":"Not applicable","PublicPrivate":"Public","TotalDegree3":4252,"UnivType":"2 year","SchoolClassifier":"NotClassified"},"FreshEnroll":{},"TuitionAndExpenses":{"FeesIndistrict":480,"FeesInstate":480,"FeesOutstate":480,"TuitionIndistrict":4623,"TuitionInstate":4623,"TuitionOutstate":5157,"RoomBoard":17864,"BookFees":942,"StickerInState":23909,"StickerOutState":24443},"AdmissionFreshmen":{"ApplicFeeAmt":0},"Admissions":{"CommonForm":"no","CoalitionForm":false,"CommonGroup":""},"FinancialAid":{"AverageDebt":8664,"DebtBalanceMedian":8664,"PcFedLoansReceived":7,"PcFinAidReceived":41},"NetPrice":{"NetAverage":11896,"Income1":8414,"Income2":7796,"Income3":9415,"Income4":11385,"Income5":16913},"CalculatedFields":{"AcceptanceRate":-1,"SATMin":0,"SATMax":0,"SATAvg":0,"ACTAvg":0,"ACTMin":0,"ACTMax":0},"Sports":{},"Degrees":null,"ApplicationDetails":{"StandardizedTests":{"SATorACT":{"Value":"NotRequired"},"WithWriting":{"Value":"NotRequired"},"SubjectTests":{"Value":"NotRequired"}},"SupplementalRequirements":{"EssayOrStatement":{"Value":"NotRequired"},"Resume":{"Value":"NotRequired"},"Portfolio":{"Value":"NotRequired"},"Interview":{"Value":"NotRequired"},"AuditionOrPortfolioReview":{"Value":"NotRequired"}}},"ApplicationRounds":[{"Name":"Rolling","Type":"Rolling","DueDate":{"Day":0,"Month":0},"Binding":false}]}