{"Scid":9000101,"Name":"ETI Technical College","Address":"2076 Youngstown Warren Rd","City":"Niles","State":"OH","Zip":"44446-4398","WwwUrl":"https://eticollege.edu/","Opeid":"03079000","Opeid6":"030790","Iped":"200590","Setting":"Suburban","Location":{"type":"Point","coordinates":[-80.72321319580078,41.18693923950195]},"Country":"United States","ScoirApplyEnabled":false,"DisplayAsScoirApply":false,"CoalitionMember":false,"GeneralInfo":{"AdmPhone":"","AdmEmail":"","AdmFax":"","FinPhone":"","FtDegree3":182,"HBCU":false,"HonorsCollege":"","OthRelig":"Not applicable","PublicPrivate":"Private - For-profit","TotalDegree3":182,"UnivType":"2 year","SchoolClassifier":"CareerAndTrade"},"FreshEnroll":{},"TuitionAndExpenses":{"FeesIndistrict":750,"FeesInstate":750,"FeesOutstate":750,"TuitionIndistrict":10310,"TuitionInstate":10310,"TuitionOutstate":10310,"RoomBoard":5000,"BookFees":3450,"StickerInState":19510,"StickerOutState":19510},"AdmissionFreshmen":{"ApplicFeeAmt":0},"Admissions":{"CommonForm":"no","CoalitionForm":false,"CommonGroup":""},"FinancialAid":{"AverageDebt":0,"DebtBalanceMedian":0,"PcFedLoansReceived":71,"PcFinAidReceived":86},"NetPrice":{"NetAverage":13775,"Income1":13283,"Income2":0,"Income3":15495,"Income4":0,"Income5":0},"CalculatedFields":{"AcceptanceRate":-1,"SATMin":0,"SATMax":0,"SATAvg":0,"ACTAvg":0,"ACTMin":0,"ACTMax":0},"Sports":{},"Degrees":null,"ApplicationDetails":{"StandardizedTests":{"SATorACT":{"Value":"NotSpecified"},"WithWriting":{"Value":"NotSpecified"},"SubjectTests":{"Value":"NotSpecified"}},"SupplementalRequirements":{"EssayOrStatement":{"Value":"NotSpecified"},"Resume":{"Value":"NotSpecified"},"Portfolio":{"Value":"NotSpecified"},"Interview":{"Value":"NotSpecified"},"AuditionOrPortfolioReview":{"Value":"NotSpecified"}}},"ApplicationRounds":[{"Name":"Rolling","Type":"Rolling","DueDate":{"Day":0,"Month":0},"Binding":false}]}