{"Scid":9002535,"Name":"Jna Institute of Culinary Arts","Address":"1212 S Broad St","City":"Philadelphia","State":"PA","Zip":"19146","WwwUrl":"https://www.culinaryarts.edu/","Opeid":"03103300","Opeid6":"031033","Iped":"419341","Setting":"City","Location":{"type":"Point","coordinates":[-75.16767883300781,39.93523025512695]},"Country":"United States","ScoirApplyEnabled":false,"DisplayAsScoirApply":false,"CoalitionMember":false,"GeneralInfo":{"AdmPhone":"","AdmEmail":"","AdmFax":"","FinPhone":"","FtDegree3":31,"HBCU":false,"HonorsCollege":"","OthRelig":"Not applicable","PublicPrivate":"Private - For-profit","TotalDegree3":31,"UnivType":"2 year","SchoolClassifier":"CareerAndTrade"},"FreshEnroll":{},"TuitionAndExpenses":{"FeesIndistrict":75,"FeesInstate":75,"FeesOutstate":75,"TuitionIndistrict":14500,"TuitionInstate":14500,"TuitionOutstate":14500,"RoomBoard":12960,"BookFees":1705,"StickerInState":29240,"StickerOutState":29240},"AdmissionFreshmen":{"ApplicFeeAmt":0},"Admissions":{"CommonForm":"no","CoalitionForm":false,"CommonGroup":""},"FinancialAid":{"AverageDebt":0,"DebtBalanceMedian":0,"PcFedLoansReceived":71,"PcFinAidReceived":56},"NetPrice":{"NetAverage":13860,"Income1":13860,"Income2":0,"Income3":0,"Income4":20438,"Income5":20438},"CalculatedFields":{"AcceptanceRate":-1,"SATMin":0,"SATMax":0,"SATAvg":0,"ACTAvg":0,"ACTMin":0,"ACTMax":0},"Sports":{},"Degrees":null,"ApplicationDetails":{"StandardizedTests":{"SATorACT":{"Value":"NotSpecified"},"WithWriting":{"Value":"NotSpecified"},"SubjectTests":{"Value":"NotSpecified"}},"SupplementalRequirements":{"EssayOrStatement":{"Value":"NotSpecified"},"Resume":{"Value":"NotSpecified"},"Portfolio":{"Value":"NotSpecified"},"Interview":{"Value":"NotSpecified"},"AuditionOrPortfolioReview":{"Value":"NotSpecified"}}},"ApplicationRounds":[{"Name":"Rolling","Type":"Rolling","DueDate":{"Day":0,"Month":0},"Binding":false}]}