{"Scid":9002211,"Name":"ICPR Junior College (Arecibo)","Address":"20 San Patricio","City":"Arecibo","State":"PR","Zip":"00614-0067","WwwUrl":"http://www.icprjc.edu/","Opeid":"01194001","Opeid6":"011940","Iped":"242130","Setting":"City","Location":{"type":"Point","coordinates":[-66.75932312011719,18.478059768676758]},"Country":"Puerto Rico","ScoirApplyEnabled":false,"DisplayAsScoirApply":false,"CoalitionMember":false,"GeneralInfo":{"AdmPhone":"","AdmEmail":"","AdmFax":"","FinPhone":"","FtDegree3":348,"HBCU":false,"HonorsCollege":"","OthRelig":"Not applicable","PublicPrivate":"Private - For-profit","TotalDegree3":348,"UnivType":"2 year","SchoolClassifier":"CareerAndTrade"},"FreshEnroll":{},"TuitionAndExpenses":{"FeesIndistrict":0,"FeesInstate":0,"FeesOutstate":0,"TuitionIndistrict":8060,"TuitionInstate":8060,"TuitionOutstate":8060,"RoomBoard":6250,"BookFees":2964,"StickerInState":17274,"StickerOutState":17274},"AdmissionFreshmen":{"ApplicFeeAmt":0},"Admissions":{"CommonForm":"no","CoalitionForm":false,"CommonGroup":""},"FinancialAid":{"AverageDebt":0,"DebtBalanceMedian":0,"PcFinAidReceived":100},"NetPrice":{"NetAverage":5317,"Income1":4843,"Income2":5023,"Income3":5289,"Income4":0,"Income5":0},"CalculatedFields":{"AcceptanceRate":-1,"SATMin":0,"SATMax":0,"SATAvg":0,"ACTAvg":0,"ACTMin":0,"ACTMax":0},"Sports":{},"Degrees":null,"ApplicationDetails":{"StandardizedTests":{"SATorACT":{"Value":"NotSpecified"},"WithWriting":{"Value":"NotSpecified"},"SubjectTests":{"Value":"NotSpecified"}},"SupplementalRequirements":{"EssayOrStatement":{"Value":"NotSpecified"},"Resume":{"Value":"NotSpecified"},"Portfolio":{"Value":"NotSpecified"},"Interview":{"Value":"NotSpecified"},"AuditionOrPortfolioReview":{"Value":"NotSpecified"}}},"ApplicationRounds":[{"Name":"Rolling","Type":"Rolling","DueDate":{"Day":0,"Month":0},"Binding":false}]}